batrachomyomachia/__init__.py
batrachomyomachia/allowlist.py
batrachomyomachia/cli.py
batrachomyomachia/config.py
batrachomyomachia/cron.py
batrachomyomachia/default-settings.yml
batrachomyomachia/do-not-add-mycli.py
batrachomyomachia/email.py
batrachomyomachia/forgejo_api_ops.py
batrachomyomachia/local_git_ops.py
batrachomyomachia/templates.py
batrachomyomachia/utilities.py
batrachomyomachia/webhook.py
batrachomyomachia/templates/pr-cover.j2
batrachomyomachia/templates/pr-new-version.j2
batrachomyomachia/templates/pr-summary-email-text.j2
batrachomyomachia/templates/pr-versions.j2
batrachomyomachia/templates/pr-welcome.j2
batrachomyomachia-2025.8.27.dist-info/METADATA
batrachomyomachia-2025.8.27.dist-info/WHEEL
batrachomyomachia-2025.8.27.dist-info/entry_points.txt
batrachomyomachia-2025.8.27.dist-info/top_level.txt
batrachomyomachia-2025.8.27.dist-info/RECORD
