Metadata-Version: 2.4
Name: batrachomyomachia
Version: 2025.8.27
Summary: Add your description here
License-Expression: GPL-3.0-or-later
Requires-Python: >=3.13
Requires-Dist: asgiref>=3.9.1
Requires-Dist: celery[gevent,redis]>=5.3.3
Requires-Dist: click>=8.2.1
Requires-Dist: dynaconf>=3.2.11
Requires-Dist: emails>=0.6
Requires-Dist: filelock>=3.19.1
Requires-Dist: flask[async]>=3.1.2
Requires-Dist: flower>=2.0.0
Requires-Dist: gitpython>=3.1.45
Requires-Dist: jinja2>=3.1.6
Requires-Dist: platformdirs>=4.3.8
Requires-Dist: pyforgejo>=2.0.4
Requires-Dist: python-dotenv>=1.1.1
Requires-Dist: ruamel-yaml>=0.18
Requires-Dist: uvicorn[standard]>=0.35.0
Provides-Extra: dev
Requires-Dist: pytest; extra == "dev"
Requires-Dist: mypy; extra == "dev"
Requires-Dist: fakeredis; extra == "dev"
Requires-Dist: types-click; extra == "dev"
Requires-Dist: ruff; extra == "dev"
Requires-Dist: pytest-cov; extra == "dev"
Requires-Dist: tox; extra == "dev"
